{
  "$schema": "https://developer.microsoft.com/json-schemas/fabric/item/report/definition/visualContainer/2.7.0/schema.json",
  "name": "0ad84d1fc5caec50720e",
  "position": {
    "x": 401,
    "y": 329,
    "z": 2000,
    "height": 390,
    "width": 879,
    "tabOrder": 0
  },
  "visual": {
    "visualType": "clusteredColumnChart",
    "query": {
      "queryState": {
        "Category": {
          "projections": [
            {
              "field": {
                "Column": {
                  "Expression": {
                    "SourceRef": {
                      "Entity": "Product_dim"
                    }
                  },
                  "Property": "product_category"
                }
              },
              "queryRef": "Product_dim.product_category",
              "nativeQueryRef": "product_category",
              "active": true
            },
            {
              "field": {
                "Column": {
                  "Expression": {
                    "SourceRef": {
                      "Entity": "Product_dim"
                    }
                  },
                  "Property": "product_type"
                }
              },
              "queryRef": "Product_dim.product_type",
              "nativeQueryRef": "product_type",
              "active": false
            }
          ]
        },
        "Y": {
          "projections": [
            {
              "field": {
                "Measure": {
                  "Expression": {
                    "SourceRef": {
                      "Entity": "_01_core_measures"
                    }
                  },
                  "Property": "Total Sales"
                }
              },
              "queryRef": "_01_core_measures.Total Sales",
              "nativeQueryRef": "Total Sales"
            }
          ]
        }
      },
      "sortDefinition": {
        "sort": [
          {
            "field": {
              "Column": {
                "Expression": {
                  "SourceRef": {
                    "Entity": "Product_dim"
                  }
                },
                "Property": "product_category"
              }
            },
            "direction": "Ascending"
          },
          {
            "field": {
              "Column": {
                "Expression": {
                  "SourceRef": {
                    "Entity": "Product_dim"
                  }
                },
                "Property": "product_type"
              }
            },
            "direction": "Ascending"
          }
        ],
        "isDefaultSort": true
      }
    },
    "objects": {
      "categoryAxis": [
        {
          "properties": {
            "maxMarginFactor": {
              "expr": {
                "Literal": {
                  "Value": "35L"
                }
              }
            },
            "showAxisTitle": {
              "expr": {
                "Literal": {
                  "Value": "false"
                }
              }
            }
          }
        }
      ],
      "valueAxis": [
        {
          "properties": {
            "showAxisTitle": {
              "expr": {
                "Literal": {
                  "Value": "false"
                }
              }
            }
          }
        }
      ],
      "labels": [
        {
          "properties": {
            "show": {
              "expr": {
                "Literal": {
                  "Value": "true"
                }
              }
            },
            "optimizeLabelDisplay": {
              "expr": {
                "Literal": {
                  "Value": "false"
                }
              }
            },
            "labelOverflow": {
              "expr": {
                "Literal": {
                  "Value": "false"
                }
              }
            },
            "enableTitleDataLabel": {
              "expr": {
                "Literal": {
                  "Value": "false"
                }
              }
            },
            "titleContentType": {
              "expr": {
                "Literal": {
                  "Value": "'Custom'"
                }
              }
            }
          }
        },
        {
          "properties": {
            "dynamicLabelTitle": {
              "expr": {
                "Measure": {
                  "Expression": {
                    "SourceRef": {
                      "Entity": "_02_nested_measures"
                    }
                  },
                  "Property": "bar chart label (product category)"
                }
              }
            }
          },
          "selector": {
            "data": [
              {
                "dataViewWildcard": {
                  "matchingOption": 1
                }
              }
            ],
            "highlightMatching": 1
          }
        }
      ]
    },
    "visualContainerObjects": {
      "title": [
        {
          "properties": {
            "titleWrap": {
              "expr": {
                "Literal": {
                  "Value": "true"
                }
              }
            },
            "fontSize": {
              "expr": {
                "Literal": {
                  "Value": "12D"
                }
              }
            },
            "italic": {
              "expr": {
                "Literal": {
                  "Value": "true"
                }
              }
            },
            "fontFamily": {
              "expr": {
                "Literal": {
                  "Value": "'''Segoe UI Semibold'', wf_segoe-ui_semibold, helvetica, arial, sans-serif'"
                }
              }
            }
          }
        }
      ],
      "background": [
        {
          "properties": {
            "show": {
              "expr": {
                "Literal": {
                  "Value": "true"
                }
              }
            },
            "transparency": {
              "expr": {
                "Literal": {
                  "Value": "0D"
                }
              }
            }
          }
        }
      ],
      "border": [
        {
          "properties": {
            "width": {
              "expr": {
                "Literal": {
                  "Value": "1D"
                }
              }
            }
          }
        }
      ]
    },
    "drillFilterOtherVisuals": true
  }
}